{
    "scan_info": {
        "target": "yahoo.com",
        "domain": "yahoo.com",
        "type": "domain",
        "command": "whois",
        "start_time": "2025-12-03T14:47:12.082336",
        "version": "3.4",
        "end_time": "2025-12-03T14:47:12.627580"
    },
    "modules": {
        "whois": {
            "domain": "yahoo.com",
            "query_timestamp": "2025-12-03T14:47:12.082443",
            "raw_query": {
                "domain": "yahoo.com",
                "raw_output": "   Domain Name: YAHOO.COM\r\n   Registry Domain ID: 3643624_DOMAIN_COM-VRSN\r\n   Registrar WHOIS Server: whois.markmonitor.com\r\n   Registrar URL: http://www.markmonitor.com\r\n   Updated Date: 2024-12-18T09:10:56Z\r\n   Creation Date: 1995-01-18T05:00:00Z\r\n   Registry Expiry Date: 2026-01-19T05:00:00Z\r\n   Registrar: MarkMonitor Inc.\r\n   Registrar IANA ID: 292\r\n   Registrar Abuse Contact Email: abusecomplaints@markmonitor.com\r\n   Registrar Abuse Contact Phone: +1.2086851750\r\n   Domain Status: clientDeleteProhibited https://icann.org/epp#clientDeleteProhibited\r\n   Domain Status: clientTransferProhibited https://icann.org/epp#clientTransferProhibited\r\n   Domain Status: clientUpdateProhibited https://icann.org/epp#clientUpdateProhibited\r\n   Domain Status: serverDeleteProhibited https://icann.org/epp#serverDeleteProhibited\r\n   Domain Status: serverTransferProhibited https://icann.org/epp#serverTransferProhibited\r\n   Domain Status: serverUpdateProhibited https://icann.org/epp#serverUpdateProhibited\r\n   Name Server: NS1.YAHOO.COM\r\n   Name Server: NS2.YAHOO.COM\r\n   Name Server: NS3.YAHOO.COM\r\n   Name Server: NS4.YAHOO.COM\r\n   Name Server: NS5.YAHOO.COM\r\n   DNSSEC: unsigned\r\n   URL of the ICANN Whois Inaccuracy Complaint Form: https://www.icann.org/wicf/\r\n>>> Last update of whois database: 2025-12-03T12:46:55Z <<<\r\n\r\nFor more information on Whois status codes, please visit https://icann.org/epp\r\n\r\nNOTICE: The expiration date displayed in this record is the date the\r\nregistrar's sponsorship of the domain name registration in the registry is\r\ncurrently set to expire. This date does not necessarily reflect the expiration\r\ndate of the domain name registrant's agreement with the sponsoring\r\nregistrar.  Users may consult the sponsoring registrar's Whois database to\r\nview the registrar's reported date of expiration for this registration.\r\n\r\nTERMS OF USE: You are not authorized to access or query our Whois\r\ndatabase through the use of electronic processes that are high-volume and\r\nautomated except as reasonably necessary to register domain names or\r\nmodify existing registrations; the Data in VeriSign Global Registry\r\nServices' (\"VeriSign\") Whois database is provided by VeriSign for\r\ninformation purposes only, and to assist persons in obtaining information\r\nabout or related to a domain name registration record. VeriSign does not\r\nguarantee its accuracy. By submitting a Whois query, you agree to abide\r\nby the following terms of use: You agree that you may use this Data only\r\nfor lawful purposes and that under no circumstances will you use this Data\r\nto: (1) allow, enable, or otherwise support the transmission of mass\r\nunsolicited, commercial advertising or solicitations via e-mail, telephone,\r\nor facsimile; or (2) enable high volume, automated, electronic processes\r\nthat apply to VeriSign (or its computer systems). The compilation,\r\nrepackaging, dissemination or other use of this Data is expressly\r\nprohibited without the prior written consent of VeriSign. You agree not to\r\nuse electronic processes that are automated and high-volume to access or\r\nquery the Whois database except as reasonably necessary to register\r\ndomain names or modify existing registrations. VeriSign reserves the right\r\nto restrict your access to the Whois database in its sole discretion to ensure\r\noperational stability.  VeriSign may restrict or terminate your access to the\r\nWhois database for failure to abide by these terms of use. VeriSign\r\nreserves the right to modify these terms at any time.\r\n\r\nThe Registry database contains ONLY .COM, .NET, .EDU domains and\r\nRegistrars.\r\n",
                "whois_server": "whois.verisign-grs.com",
                "query_time": "2025-12-03T14:47:12.082506",
                "response_time": 0.24624323844909668,
                "error": null,
                "success": true
            },
            "parsed_data": {
                "domain_name": "yahoo.com",
                "registrar": "MarkMonitor Inc.",
                "creation_date": "1995-01-18T05:00:00Z",
                "expiration_date": "2026-01-19T05:00:00Z",
                "updated_date": "2024-12-18T09:10:56Z",
                "name_servers": [
                    "NS1.YAHOO.COM",
                    "NS2.YAHOO.COM",
                    "NS3.YAHOO.COM",
                    "NS4.YAHOO.COM",
                    "NS5.YAHOO.COM"
                ],
                "status": [
                    "clientDeleteProhibited https://icann.org/epp#clientDeleteProhibited",
                    "clientTransferProhibited https://icann.org/epp#clientTransferProhibited",
                    "clientUpdateProhibited https://icann.org/epp#clientUpdateProhibited",
                    "serverDeleteProhibited https://icann.org/epp#serverDeleteProhibited",
                    "serverTransferProhibited https://icann.org/epp#serverTransferProhibited",
                    "serverUpdateProhibited https://icann.org/epp#serverUpdateProhibited"
                ],
                "registrar_iana_id": "292",
                "dnssec": "unsigned",
                "creation_date_standardized": "1995-01-18T05:00:00",
                "domain_age_days": 11277,
                "domain_age_years": 30.87,
                "domain_age_category": "established",
                "expiration_date_standardized": "2026-01-19T05:00:00",
                "updated_date_standardized": "2024-12-18T09:10:56"
            },
            "domain_age": {
                "domain": "yahoo.com",
                "creation_date": "1995-01-18T05:00:00",
                "expiration_date": "2026-01-19T05:00:00",
                "domain_age_days": 11277,
                "domain_age_years": 30.87,
                "domain_age_category": "established",
                "days_until_expiry": 46,
                "error": null,
                "creation_date_original": "1995-01-18T05:00:00Z",
                "expiration_date_original": "2026-01-19T05:00:00Z"
            },
            "owner_info": {
                "domain": "yahoo.com",
                "registrant_info": {
                    "registrar": "MarkMonitor Inc.",
                    "name_servers": [
                        "NS1.YAHOO.COM",
                        "NS2.YAHOO.COM",
                        "NS3.YAHOO.COM",
                        "NS4.YAHOO.COM",
                        "NS5.YAHOO.COM"
                    ],
                    "status": [
                        "clientDeleteProhibited https://icann.org/epp#clientDeleteProhibited",
                        "clientTransferProhibited https://icann.org/epp#clientTransferProhibited",
                        "clientUpdateProhibited https://icann.org/epp#clientUpdateProhibited",
                        "serverDeleteProhibited https://icann.org/epp#serverDeleteProhibited",
                        "serverTransferProhibited https://icann.org/epp#serverTransferProhibited",
                        "serverUpdateProhibited https://icann.org/epp#serverUpdateProhibited"
                    ]
                },
                "admin_info": {},
                "tech_info": {},
                "privacy_protection": false,
                "error": null
            },
            "summary": {
                "domain_registered": true,
                "registrar_found": true,
                "name_servers_found": true,
                "owner_info_found": true,
                "privacy_protection": false,
                "lookup_successful": true
            },
            "error": null,
            "duration": 0.545067548751831,
            "status": "success"
        }
    }
}